{
  "id": "charmed-life_sct13_f5",
  "schemaVersion": 1,
  "fragmentId": "sha1:76079b9b6e311eeb0e8756e62620f7bc69ce3adb",
  "generationHash": "sha1:2ce838f72dd8f7e4a44313aa3b8aeacb4b620d53",
  "title": "Charmed Life - Chapter 10 (Fragment 5)",
  "text": "“They aren’t,” said Cat. “But I wish they were.” He took a lathe out of the wreckage of the house and slashed at the chestnut cases with it. He missed, but he must have shaken them. Eight or so dropped off the tree and went plomp on the ground below.\n\n“Who says they’re not ripe?” said Janet, leaning down.\n\nCat craned out of the tree and saw brown shiny chestnuts showing in the split green cases. “Oh, hurray!” He came down the tree like a monkey, and Janet crashed after him, with her hair full of twigs. They scooped up the chestnuts greedily—wonderful chestnuts with grain on them like the contours in a map.\n\n“A skewer!” Janet moaned. “My kingdom for a skewer! We can thread them on my bootlaces.”\n\n“Here’s a skewer,” said Cat. There was one lying on the ground by his left hand. It must have fallen out of the tree house.\n\nThey drilled chestnuts furiously. They took the laces out of Gwendolen’s second-best boots. They discovered the rules of the game were the same in both their worlds, and they went to the formal garden and held a battle royal there on the gravel path. As Janet firmly smashed Cat’s last chestnut and yelled, “Mine! Mine’s a sevener now!” Millie came around a corner past a yew tree and stood laughing at them.\n\n“Do you know, I wouldn’t have thought the chestnuts were ripe yet. But it’s been a lovely summer.”\n\nJanet looked at her in consternation. She had no idea who this plump lady in the beautiful flowered silk dress could be.\n\n“Hallo, Millie ,” said Cat. Not that this helped Janet much.\n\nMillie smiled and opened the handbag she was carrying. “There are three things Gwendolen needs, I think. Here.” She handed Janet two safety pins and a packet of bootlaces. “I always believe in being prepared.”\n\n“Th-thanks,” Janet stammered. She was horribly conscious of her gaping boots, her twig-filled hair, and the two trailing strips of petticoat. She was even more confused by not knowing who Millie was.\n\nCat knew that. He knew by now that Janet was one of those people who are not happy unless they have an explanation for everything. So he said fulsomely to Millie, “I do think Roger and Julia are lucky, having a mother like you, Millie.”\n\nMillie beamed and Janet looked enlightened. Cat felt dishonest. He did think that, but he would never have dreamed of saying it but for Janet.\n\nHaving gathered that Millie was Chrestomanci’s wife, Janet was quite unable to resist going on and gathering as much more information as she could. “Millie,” she said, “were Cat’s parents first cousins like—I mean, were they? And what relation is Cat to you?”\n\n“That sounds like those questions they ask you to find out how clever you are,” said Millie. “And I don’t know the answer, Gwendolen. It’s my husband’s family you’re related to, you see, and I don’t know too much about them. We need Chrestomanci here to explain, really.”\n\nAs it happened, Chrestomanci came through the doorway in the garden wall at that moment. Millie rustled up to him, beaming.\n\n“My love, we were needing you.”\n\nJanet, who had her head down, trying to pin her petticoats, glanced up at Chrestomanci and then looked thoughtfully down at the path, as if the stones and sand there had suddenly become rather interesting.\n\n“It’s quite simple,” Chrestomanci said, when Millie had explained the question. “Frank and Caroline Chant were my cousins—and first cousins to one another too, of course. When they insisted on getting married, my family made a great fuss, and my uncles cut them off without a shilling in a thoroughly old-fashioned way. It is, you see, rather a bad thing for cousins to marry when there’s witchcraft in the family. Not that cutting them off made the slightest difference, of course.” He smiled at Cat. He seemed thoroughly friendly. “Does that answer the question?”\n\nCat had an inkling of how Gwendolen had felt. It was confusing and exasperating the way Chrestomanci would seem friendly when one ought to have been in disgrace. He could not resist asking, “Is Euphemia all right?”\n\nThen he wished he had not asked. Chrestomanci’s smile snapped off like a light. “Yes. She’s feeling better now. You show touching concern, Eric. I believe you were so sorry for her that you hid her in a wardrobe?”\n\n“My love, don’t be so terrifying,” Millie said, hooking her arm through Chrestomanci’s. “It was an accident, and it’s all over now.” She led him away down the path. But, just before they went out of sight behind a yew tree, Chrestomanci turned and looked over his shoulder at Cat and Janet. It was his bewildered look, but it was far from reassuring.\n\n“Hot-cross bun-wrappers! Jiminy purple creepers!” Janet whispered. “I’m beginning to hardly dare move in this place!” She finished pinning her petticoat. When Millie and Chrestomanci had had nearly a minute in which to walk out of hearing, she said, “She’s sweet—Millie—an absolute honey. But him! Cat, is it possible Chrestomanci is a rather powerful enchanter?”\n\n“I don’t think he is,” said Cat. “Why?”\n\n“Well,” said Janet, “partly it’s the feeling he gives—”\n\n“I don’t get a feeling,” said Cat. “I’m just frightened of him.”\n\n“That’s it ,” said Janet. “You’re probably muddled anyhow from having lived with witches all your life. But it isn’t only a feeling. Have you noticed how he always comes when people call him? He’s done it twice now.”\n\n“Those were two complete accidents,” said Cat. “You can’t build ideas on accidents.”\n\n“He disguises it quite well, I admit,” said Janet. “He comes looking as if it was something else he was doing, but—”\n\n“Oh, do shut up! You’re getting as bad as Gwendolen. She couldn’t stop thinking of him for a moment,” Cat said crossly.\n\nJanet pounded her open right boot on the gravel. “I am not Gwendolen! I’m not even really like her! Get that into your fat head, will you!”\n\nCat started to laugh.\n\n“Why are you laughing?” said Janet.\n\n“Gwendolen always stamps when she’s angry too,” said Cat.\n\n“Gah!” said Janet.",
  "meta": {
    "bookId": "charmed-life",
    "bookTitle": "Charmed Life",
    "bookLanguage": "en",
    "author": "Diana Wynne Jones",
    "seriesId": "standalone",
    "sectionIndex": 13,
    "sectionTitle": "Chapter 10",
    "fragmentIndex": 5,
    "fragmentsInSection": 5,
    "sourceFile": "OEBPS/chapter10.xhtml",
    "stats": {
      "wordCount": 1030,
      "uniqueWordCount": 527,
      "paragraphCount": 35,
      "vocabularyCount": 42,
      "levelDistribution": {
        "A1": 0,
        "A2": 1,
        "B1": 5,
        "B2": 32,
        "C1": 3,
        "C2": 1
      }
    }
  },
  "vocabulary": [
    {
      "word": "all over",
      "lemma": "all over",
      "lemmaId": "all_over",
      "pos": "phrase",
      "type": "phrase",
      "source": "fixed_expression",
      "wordKey": "all_over_phrase",
      "level": "B1",
      "translations": {
        "ru": {
          "translation": "Всё кончено"
        }
      },
      "example": "“It was an accident, and it’s all over now.",
      "exampleStart": 4303,
      "exampleEnd": 4346,
      "phraseMatch": {
        "text": "all over",
        "startInExample": 30,
        "endInExample": 38
      },
      "levelSource": "phrase_fallback",
      "ipa": "ɔːl ˈəʊvə"
    },
    {
      "word": "believe in",
      "lemma": "believe in",
      "lemmaId": "believe_in",
      "pos": "phrasal_verb",
      "type": "phrasal_verb",
      "source": "dictionary_phrasal",
      "wordKey": "believe_in_phrasal_verb",
      "level": "B2",
      "translations": {
        "ru": {
          "translation": "верить в"
        }
      },
      "example": "“I always believe in being prepared.",
      "exampleStart": 1696,
      "exampleEnd": 1732,
      "phraseMatch": {
        "text": "believe in",
        "startInExample": 10,
        "endInExample": 20
      },
      "levelSource": "dictionary_phrase",
      "ipa": "bɪˈliːv ɪn"
    },
    {
      "word": "bewildered",
      "lemma": "bewilder",
      "lemmaId": "bewilder",
      "pos": "adjective",
      "source": "word",
      "wordKey": "bewilder_adjective",
      "level": "C1",
      "translations": {
        "ru": {
          "translation": "недоумение"
        }
      },
      "example": "It was his bewildered look, but it was far from reassuring.",
      "exampleStart": 4506,
      "exampleEnd": 4565,
      "matchedForm": "bewildered",
      "levelSource": "vocabulary_index",
      "difficultyScore": 1,
      "difficultySource": "zipf"
    },
    {
      "word": "build on",
      "lemma": "build on",
      "lemmaId": "build_on",
      "pos": "phrasal_verb",
      "type": "phrasal_verb",
      "source": "dictionary_phrasal",
      "wordKey": "build_on_phrasal_verb",
      "level": "B2",
      "translations": {
        "ru": {
          "translation": "Развивайте"
        }
      },
      "example": "“You can’t build ideas on accidents.",
      "exampleStart": 5361,
      "exampleEnd": 5397,
      "phraseMatch": {
        "text": "build ideas on",
        "startInExample": 11,
        "endInExample": 25
      },
      "levelSource": "dictionary_phrase",
      "ipa": "bɪld ɒn"
    },
    {
      "word": "came around",
      "lemma": "come around",
      "lemmaId": "come_around",
      "pos": "phrasal_verb",
      "type": "phrasal_verb",
      "source": "dictionary_phrasal",
      "wordKey": "come_around_phrasal_verb",
      "level": "B2",
      "translations": {
        "ru": {
          "translation": "пришёл"
        }
      },
      "example": "” Millie came around a corner past a yew tree and stood laughing at them.",
      "exampleStart": 1165,
      "exampleEnd": 1238,
      "phraseMatch": {
        "text": "came around",
        "startInExample": 9,
        "endInExample": 20
      },
      "levelSource": "dictionary_phrase",
      "ipa": "kʌm əˈraʊnd"
    },
    {
      "word": "came down",
      "lemma": "come down",
      "lemmaId": "come_down",
      "pos": "phrasal_verb",
      "type": "phrasal_verb",
      "source": "dictionary_phrasal",
      "wordKey": "come_down_phrasal_verb",
      "level": "B2",
      "translations": {
        "ru": {
          "translation": "спустился"
        }
      },
      "example": "” He came down the tree like a monkey, and Janet crashed after him, with her hair full of twigs.",
      "exampleStart": 411,
      "exampleEnd": 507,
      "phraseMatch": {
        "text": "came down",
        "startInExample": 5,
        "endInExample": 14
      },
      "levelSource": "dictionary_phrase",
      "ipa": "kʌm daʊn"
    },
    {
      "word": "came through",
      "lemma": "come through",
      "lemmaId": "come_through",
      "pos": "phrasal_verb",
      "type": "phrasal_verb",
      "source": "dictionary_phrasal",
      "wordKey": "come_through_phrasal_verb",
      "level": "B2",
      "translations": {
        "ru": {
          "translation": "Прошёл"
        }
      },
      "example": "”\n\nAs it happened, Chrestomanci came through the doorway in the garden wall at that moment.",
      "exampleStart": 2849,
      "exampleEnd": 2940,
      "phraseMatch": {
        "text": "came through",
        "startInExample": 32,
        "endInExample": 44
      },
      "levelSource": "dictionary_phrase",
      "ipa": "kʌm θruː"
    },
    {
      "word": "cutting off",
      "lemma": "cut off",
      "lemmaId": "cut_off",
      "pos": "phrasal_verb",
      "type": "phrasal_verb",
      "source": "dictionary_phrasal",
      "wordKey": "cut_off_phrasal_verb",
      "level": "B2",
      "translations": {
        "ru": {
          "translation": "Отключение"
        }
      },
      "example": "Not that cutting them off made the slightest difference, of course.",
      "exampleStart": 3632,
      "exampleEnd": 3699,
      "phraseMatch": {
        "text": "cutting them off",
        "startInExample": 9,
        "endInExample": 25
      },
      "levelSource": "dictionary_phrase",
      "ipa": "kʌt ɒf"
    },
    {
      "word": "do up",
      "lemma": "do up",
      "lemmaId": "do_up",
      "pos": "phrasal_verb",
      "type": "phrasal_verb",
      "source": "dictionary_phrasal",
      "wordKey": "do_up_phrasal_verb",
      "level": "B2",
      "translations": {
        "ru": {
          "translation": "Одеться"
        }
      },
      "example": "“He comes looking as if it was something else he was doing, but—”\n\n“Oh, do shut up!",
      "exampleStart": 5451,
      "exampleEnd": 5534,
      "phraseMatch": {
        "text": "do shut up",
        "startInExample": 72,
        "endInExample": 82
      },
      "levelSource": "dictionary_phrase",
      "ipa": "duː ʌp"
    },
    {
      "word": "dreamed of",
      "lemma": "dream of",
      "lemmaId": "dream_of",
      "pos": "phrasal_verb",
      "type": "phrasal_verb",
      "source": "dictionary_phrasal",
      "wordKey": "dream_of_phrasal_verb",
      "level": "B2",
      "translations": {
        "ru": {
          "translation": "мечтался"
        }
      },
      "example": "He did think that, but he would never have dreamed of saying it but for Janet.",
      "exampleStart": 2238,
      "exampleEnd": 2316,
      "phraseMatch": {
        "text": "dreamed of",
        "startInExample": 43,
        "endInExample": 53
      },
      "levelSource": "dictionary_phrase",
      "ipa": "driːm ɒv"
    },
    {
      "word": "dropped off",
      "lemma": "drop off",
      "lemmaId": "drop_off",
      "pos": "phrasal_verb",
      "type": "phrasal_verb",
      "source": "dictionary_phrasal",
      "wordKey": "drop_off_phrasal_verb",
      "level": "B2",
      "translations": {
        "ru": {
          "translation": "Сдали"
        }
      },
      "example": "Eight or so dropped off the tree and went plomp on the ground below.",
      "exampleStart": 182,
      "exampleEnd": 250,
      "phraseMatch": {
        "text": "dropped off",
        "startInExample": 12,
        "endInExample": 23
      },
      "levelSource": "dictionary_phrase",
      "ipa": "drɒp ɒf"
    },
    {
      "word": "exasperating",
      "lemma": "exasperate",
      "lemmaId": "exasperate",
      "pos": "adjective",
      "source": "word",
      "wordKey": "exasperate_adjective",
      "level": "C2",
      "translations": {
        "ru": {
          "translation": "раздражать"
        }
      },
      "example": "It was confusing and exasperating the way Chrestomanci would seem friendly when one ought to have been in disgrace.",
      "exampleStart": 3830,
      "exampleEnd": 3945,
      "matchedForm": "exasperating",
      "levelSource": "vocabulary_index",
      "difficultyScore": 1,
      "difficultySource": "zipf"
    },
    {
      "word": "find out",
      "lemma": "find out",
      "lemmaId": "find_out",
      "pos": "phrasal_verb",
      "type": "phrasal_verb",
      "source": "dictionary_phrasal",
      "wordKey": "find_out_phrasal_verb",
      "level": "B2",
      "translations": {
        "ru": {
          "translation": "Узнайте"
        }
      },
      "example": "”\n\n“That sounds like those questions they ask you to find out how clever you are,” said Millie.",
      "exampleStart": 2576,
      "exampleEnd": 2671,
      "phraseMatch": {
        "text": "find out",
        "startInExample": 53,
        "endInExample": 61
      },
      "levelSource": "dictionary_phrase",
      "ipa": "faɪnd aʊt"
    },
    {
      "word": "fulsomely",
      "lemma": "fulsomely",
      "lemmaId": "fulsomely",
      "pos": "adverb",
      "source": "word",
      "wordKey": "fulsomely_adverb",
      "level": "C1",
      "translations": {
        "ru": {
          "translation": "напыщенно"
        }
      },
      "example": "So he said fulsomely to Millie, “I do think Roger and Julia are lucky, having a mother like you, Millie.",
      "exampleStart": 2067,
      "exampleEnd": 2171,
      "matchedForm": "fulsomely",
      "levelSource": "difficulty_heuristic",
      "difficultyScore": 1,
      "difficultySource": "zipf",
      "ipa": "ˈfʊlsʌmli"
    },
    {
      "word": "gah",
      "lemma": "gah",
      "lemmaId": "gah",
      "pos": "verb",
      "source": "word",
      "wordKey": "gah_verb",
      "level": "A2",
      "translations": {
        "ru": {
          "translation": "га"
        }
      },
      "example": "“Gah!",
      "exampleStart": 5899,
      "exampleEnd": 5904,
      "matchedForm": "Gah",
      "levelSource": "difficulty_heuristic",
      "difficultyScore": 0.997143,
      "difficultySource": "zipf",
      "ipa": "ɡɑː"
    },
    {
      "word": "going on",
      "lemma": "go on",
      "lemmaId": "go_on",
      "pos": "phrasal_verb",
      "type": "phrasal_verb",
      "source": "dictionary_phrasal",
      "wordKey": "go_on_phrasal_verb",
      "level": "B2",
      "translations": {
        "ru": {
          "translation": "Продолжаем"
        }
      },
      "example": "Having gathered that Millie was Chrestomanci’s wife, Janet was quite unable to resist going on and gathering as much more information as she could.",
      "exampleStart": 2318,
      "exampleEnd": 2465,
      "phraseMatch": {
        "text": "going on",
        "startInExample": 86,
        "endInExample": 94
      },
      "levelSource": "dictionary_phrase",
      "ipa": "ɡəʊ ɒn"
    },
    {
      "word": "went out of",
      "lemma": "go out of",
      "lemmaId": "go_out_of",
      "pos": "phrasal_verb",
      "type": "phrasal_verb",
      "source": "dictionary_phrasal",
      "wordKey": "go_out_of_phrasal_verb",
      "level": "B2",
      "translations": {
        "ru": {
          "translation": "вышел из"
        }
      },
      "example": "But, just before they went out of sight behind a yew tree, Chrestomanci turned and looked over his shoulder at Cat and Janet.",
      "exampleStart": 4380,
      "exampleEnd": 4505,
      "phraseMatch": {
        "text": "went out of",
        "startInExample": 22,
        "endInExample": 33
      },
      "levelSource": "dictionary_phrase",
      "ipa": "ɡəʊ ˌaʊtəv"
    },
    {
      "word": "greedily",
      "lemma": "greedily",
      "lemmaId": "greedily",
      "pos": "adjective",
      "source": "word",
      "wordKey": "greedily_adjective",
      "level": "B2",
      "translations": {
        "ru": {
          "translation": "жадный"
        }
      },
      "example": "They scooped up the chestnuts greedily—wonderful chestnuts with grain on them like the contours in a map.",
      "exampleStart": 508,
      "exampleEnd": 613,
      "matchedForm": "greedily",
      "levelSource": "difficulty_heuristic",
      "difficultyScore": 1,
      "difficultySource": "zipf",
      "ipa": "ˈɡriːdili"
    },
    {
      "word": "have out",
      "lemma": "have out",
      "lemmaId": "have_out",
      "pos": "phrasal_verb",
      "type": "phrasal_verb",
      "source": "dictionary_phrasal",
      "wordKey": "have_out_phrasal_verb",
      "level": "B2",
      "translations": {
        "ru": {
          "translation": "Выйди"
        }
      },
      "example": "It must have fallen out of the tree house.",
      "exampleStart": 786,
      "exampleEnd": 828,
      "phraseMatch": {
        "text": "have fallen out",
        "startInExample": 8,
        "endInExample": 23
      },
      "levelSource": "dictionary_phrase",
      "ipa": "hav aʊt"
    },
    {
      "word": "hurray",
      "lemma": "hurray",
      "lemmaId": "hurray",
      "pos": "adjective",
      "source": "word",
      "wordKey": "hurray_adjective",
      "level": "B1",
      "translations": {
        "ru": {
          "translation": "хуррей"
        }
      },
      "example": "“Oh, hurray!",
      "exampleStart": 399,
      "exampleEnd": 411,
      "matchedForm": "hurray",
      "levelSource": "difficulty_heuristic",
      "difficultyScore": 1,
      "difficultySource": "zipf",
      "ipa": "həˈreɪ"
    },
    {
      "word": "i wish",
      "lemma": "i wish",
      "lemmaId": "i_wish",
      "pos": "phrase",
      "type": "phrase",
      "source": "fixed_expression",
      "wordKey": "i_wish_phrase",
      "level": "B1",
      "translations": {
        "ru": {
          "translation": "Хотелось бы"
        }
      },
      "example": "“But I wish they were.",
      "exampleStart": 25,
      "exampleEnd": 47,
      "phraseMatch": {
        "text": "I wish",
        "startInExample": 5,
        "endInExample": 11
      },
      "levelSource": "phrase_fallback",
      "ipa": "aɪ wɪʃ"
    },
    {
      "word": "inkling",
      "lemma": "inkling",
      "lemmaId": "inkling",
      "pos": "adjective",
      "source": "word",
      "wordKey": "inkling_adjective",
      "level": "B2",
      "translations": {
        "ru": {
          "translation": "намек"
        }
      },
      "example": "”\n\nCat had an inkling of how Gwendolen had felt.",
      "exampleStart": 3781,
      "exampleEnd": 3829,
      "matchedForm": "inkling",
      "levelSource": "difficulty_heuristic",
      "difficultyScore": 1,
      "difficultySource": "zipf",
      "ipa": "ˈɪŋklɪŋ"
    },
    {
      "word": "insisted on",
      "lemma": "insist on",
      "lemmaId": "insist_on",
      "pos": "phrasal_verb",
      "type": "phrasal_verb",
      "source": "dictionary_phrasal",
      "wordKey": "insist_on_phrasal_verb",
      "level": "B2",
      "translations": {
        "ru": {
          "translation": "настаивали на"
        }
      },
      "example": "When they insisted on getting married, my family made a great fuss, and my uncles cut them off without a shilling in a thoroughly old-fashioned way.",
      "exampleStart": 3388,
      "exampleEnd": 3536,
      "phraseMatch": {
        "text": "insisted on",
        "startInExample": 10,
        "endInExample": 21
      },
      "levelSource": "dictionary_phrase",
      "ipa": "ɪnˈsɪst ɒn"
    },
    {
      "word": "jiminy",
      "lemma": "jiminy",
      "lemmaId": "jiminy",
      "pos": "adjective",
      "source": "word",
      "wordKey": "jiminy_adjective",
      "level": "B1",
      "translations": {
        "ru": {
          "translation": "Джимини"
        }
      },
      "example": "Jiminy purple creepers!",
      "exampleStart": 4592,
      "exampleEnd": 4615,
      "matchedForm": "Jiminy",
      "levelSource": "difficulty_heuristic",
      "difficultyScore": 1,
      "difficultySource": "zipf",
      "ipa": "ˈdʒɪmɪni"
    },
    {
      "word": "laughing at",
      "lemma": "laugh at",
      "lemmaId": "laugh_at",
      "pos": "phrasal_verb",
      "type": "phrasal_verb",
      "source": "dictionary_phrasal",
      "wordKey": "laugh_at_phrasal_verb",
      "level": "B2",
      "translations": {
        "ru": {
          "translation": "смеяться над"
        }
      },
      "example": "” Millie came around a corner past a yew tree and stood laughing at them.",
      "exampleStart": 1165,
      "exampleEnd": 1238,
      "phraseMatch": {
        "text": "laughing at",
        "startInExample": 56,
        "endInExample": 67
      },
      "levelSource": "dictionary_phrase",
      "ipa": "laf at"
    },
    {
      "word": "lived with",
      "lemma": "live with",
      "lemmaId": "live_with",
      "pos": "phrasal_verb",
      "type": "phrasal_verb",
      "source": "dictionary_phrasal",
      "wordKey": "live_with_phrasal_verb",
      "level": "B2",
      "translations": {
        "ru": {
          "translation": "жил с"
        }
      },
      "example": "“You’re probably muddled anyhow from having lived with witches all your life.",
      "exampleStart": 5122,
      "exampleEnd": 5199,
      "phraseMatch": {
        "text": "lived with",
        "startInExample": 44,
        "endInExample": 54
      },
      "levelSource": "dictionary_phrase",
      "ipa": "lɪv wɪð"
    },
    {
      "word": "looked at",
      "lemma": "look at",
      "lemmaId": "look_at",
      "pos": "phrasal_verb",
      "type": "phrasal_verb",
      "source": "dictionary_phrasal",
      "wordKey": "look_at_phrasal_verb",
      "level": "B2",
      "translations": {
        "ru": {
          "translation": "смотрел"
        }
      },
      "example": "”\n\nJanet looked at her in consternation.",
      "exampleStart": 1337,
      "exampleEnd": 1377,
      "phraseMatch": {
        "text": "looked at",
        "startInExample": 9,
        "endInExample": 18
      },
      "levelSource": "dictionary_phrase",
      "ipa": "lʊk at"
    },
    {
      "word": "looked over",
      "lemma": "look over",
      "lemmaId": "look_over",
      "pos": "phrasal_verb",
      "type": "phrasal_verb",
      "source": "dictionary_phrasal",
      "wordKey": "look_over_phrasal_verb",
      "level": "B2",
      "translations": {
        "ru": {
          "translation": "посмотрел"
        }
      },
      "example": "But, just before they went out of sight behind a yew tree, Chrestomanci turned and looked over his shoulder at Cat and Janet.",
      "exampleStart": 4380,
      "exampleEnd": 4505,
      "phraseMatch": {
        "text": "looked over",
        "startInExample": 83,
        "endInExample": 94
      },
      "levelSource": "dictionary_phrase",
      "ipa": "lʊk ˈəʊvə"
    },
    {
      "word": "marry in",
      "lemma": "marry in",
      "lemmaId": "marry_in",
      "pos": "phrasal_verb",
      "type": "phrasal_verb",
      "source": "dictionary_phrasal",
      "wordKey": "marry_in_phrasal_verb",
      "level": "B2",
      "translations": {
        "ru": {
          "translation": "жениться на"
        }
      },
      "example": "It is, you see, rather a bad thing for cousins to marry when there’s witchcraft in the family.",
      "exampleStart": 3537,
      "exampleEnd": 3631,
      "phraseMatch": {
        "text": "marry when there’s witchcraft in",
        "startInExample": 50,
        "endInExample": 82
      },
      "levelSource": "dictionary_phrase",
      "ipa": "ˈmari ɪn"
    },
    {
      "word": "move in",
      "lemma": "move in",
      "lemmaId": "move_in",
      "pos": "phrasal_verb",
      "type": "phrasal_verb",
      "source": "dictionary_phrasal",
      "wordKey": "move_in_phrasal_verb",
      "level": "B2",
      "translations": {
        "ru": {
          "translation": "Вперёд"
        }
      },
      "example": "“I’m beginning to hardly dare move in this place!",
      "exampleStart": 4634,
      "exampleEnd": 4683,
      "phraseMatch": {
        "text": "move in",
        "startInExample": 30,
        "endInExample": 37
      },
      "levelSource": "dictionary_phrase",
      "ipa": "muːv ɪn"
    },
    {
      "word": "pin up",
      "lemma": "pin up",
      "lemmaId": "pin_up",
      "pos": "phrasal_verb",
      "type": "phrasal_verb",
      "source": "dictionary_phrasal",
      "wordKey": "pin_up_phrasal_verb",
      "level": "B2",
      "translations": {
        "ru": {
          "translation": "Пин-ап"
        }
      },
      "example": "”\n\nJanet, who had her head down, trying to pin her petticoats, glanced up at Chrestomanci and then looked thoughtfully down at the path, as if the stones and sand there had suddenly become rather interesting.",
      "exampleStart": 3007,
      "exampleEnd": 3215,
      "phraseMatch": {
        "text": "pin her petticoats, glanced up",
        "startInExample": 43,
        "endInExample": 73
      },
      "levelSource": "dictionary_phrase",
      "ipa": "pɪn ʌp"
    },
    {
      "word": "related to",
      "lemma": "relate to",
      "lemmaId": "relate_to",
      "pos": "phrasal_verb",
      "type": "phrasal_verb",
      "source": "dictionary_phrasal",
      "wordKey": "relate_to_phrasal_verb",
      "level": "B2",
      "translations": {
        "ru": {
          "translation": "Связан с"
        }
      },
      "example": "It’s my husband’s family you’re related to, you see, and I don’t know too much about them.",
      "exampleStart": 2713,
      "exampleEnd": 2803,
      "phraseMatch": {
        "text": "related to",
        "startInExample": 32,
        "endInExample": 42
      },
      "levelSource": "dictionary_phrase",
      "ipa": "rɪˈleɪt tuː"
    },
    {
      "word": "rustled",
      "lemma": "rustle",
      "lemmaId": "rustle",
      "pos": "adjective",
      "source": "word",
      "wordKey": "rustle_adjective",
      "level": "C1",
      "translations": {
        "ru": {
          "translation": "шорох"
        }
      },
      "example": "Millie rustled up to him, beaming.",
      "exampleStart": 2941,
      "exampleEnd": 2975,
      "matchedForm": "rustled",
      "levelSource": "vocabulary_index",
      "difficultyScore": 1,
      "difficultySource": "zipf"
    },
    {
      "word": "scooped up",
      "lemma": "scoop up",
      "lemmaId": "scoop_up",
      "pos": "phrasal_verb",
      "type": "phrasal_verb",
      "source": "dictionary_phrasal",
      "wordKey": "scoop_up_phrasal_verb",
      "level": "B2",
      "translations": {
        "ru": {
          "translation": "Подхватили"
        }
      },
      "example": "They scooped up the chestnuts greedily—wonderful chestnuts with grain on them like the contours in a map.",
      "exampleStart": 508,
      "exampleEnd": 613,
      "phraseMatch": {
        "text": "scooped up",
        "startInExample": 5,
        "endInExample": 15
      },
      "levelSource": "dictionary_phrase",
      "ipa": "skuːp ʌp"
    },
    {
      "word": "shilling",
      "lemma": "shill",
      "lemmaId": "shill",
      "pos": "adjective",
      "source": "word",
      "wordKey": "shill_adjective",
      "level": "B1",
      "translations": {
        "ru": {
          "translation": "шиллинг"
        }
      },
      "example": "When they insisted on getting married, my family made a great fuss, and my uncles cut them off without a shilling in a thoroughly old-fashioned way.",
      "exampleStart": 3388,
      "exampleEnd": 3536,
      "matchedForm": "shilling",
      "levelSource": "difficulty_heuristic",
      "difficultyScore": 1,
      "difficultySource": "zipf",
      "ipa": "ʃɪl"
    },
    {
      "word": "showing in",
      "lemma": "show in",
      "lemmaId": "show_in",
      "pos": "phrasal_verb",
      "type": "phrasal_verb",
      "source": "dictionary_phrasal",
      "wordKey": "show_in_phrasal_verb",
      "level": "B2",
      "translations": {
        "ru": {
          "translation": "Показывается в"
        }
      },
      "example": "Cat craned out of the tree and saw brown shiny chestnuts showing in the split green cases.",
      "exampleStart": 308,
      "exampleEnd": 398,
      "phraseMatch": {
        "text": "showing in",
        "startInExample": 57,
        "endInExample": 67
      },
      "levelSource": "dictionary_phrase",
      "ipa": "ʃəʊ ɪn"
    },
    {
      "word": "snapped off",
      "lemma": "snap off",
      "lemmaId": "snap_off",
      "pos": "phrasal_verb",
      "type": "phrasal_verb",
      "source": "dictionary_phrasal",
      "wordKey": "snap_off_phrasal_verb",
      "level": "B2",
      "translations": {
        "ru": {
          "translation": "отломано"
        }
      },
      "example": "Chrestomanci’s smile snapped off like a light.",
      "exampleStart": 4033,
      "exampleEnd": 4079,
      "phraseMatch": {
        "text": "snapped off",
        "startInExample": 21,
        "endInExample": 32
      },
      "levelSource": "dictionary_phrase",
      "ipa": "snap ɒf"
    },
    {
      "word": "stammered",
      "lemma": "stammer",
      "lemmaId": "stammer",
      "pos": "adjective",
      "source": "word",
      "wordKey": "stammer_adjective",
      "level": "B2",
      "translations": {
        "ru": {
          "translation": "заикание"
        }
      },
      "example": "”\n\n“Th-thanks,” Janet stammered.",
      "exampleStart": 1732,
      "exampleEnd": 1764,
      "matchedForm": "stammered",
      "levelSource": "difficulty_heuristic",
      "difficultyScore": 1,
      "difficultySource": "zipf",
      "ipa": "ˈstamə"
    },
    {
      "word": "strips of",
      "lemma": "strip of",
      "lemmaId": "strip_of",
      "pos": "phrasal_verb",
      "type": "phrasal_verb",
      "source": "dictionary_phrasal",
      "wordKey": "strip_of_phrasal_verb",
      "level": "B2",
      "translations": {
        "ru": {
          "translation": "Полоски"
        }
      },
      "example": "She was horribly conscious of her gaping boots, her twig-filled hair, and the two trailing strips of petticoat.",
      "exampleStart": 1765,
      "exampleEnd": 1876,
      "phraseMatch": {
        "text": "strips of",
        "startInExample": 91,
        "endInExample": 100
      },
      "levelSource": "dictionary_phrase",
      "ipa": "strɪp ɒv"
    },
    {
      "word": "took out",
      "lemma": "take out",
      "lemmaId": "take_out",
      "pos": "phrasal_verb",
      "type": "phrasal_verb",
      "source": "dictionary_phrasal",
      "wordKey": "take_out_phrasal_verb",
      "level": "B2",
      "translations": {
        "ru": {
          "translation": "Убрали"
        }
      },
      "example": "They took the laces out of Gwendolen’s second-best boots.",
      "exampleStart": 864,
      "exampleEnd": 921,
      "phraseMatch": {
        "text": "took the laces out",
        "startInExample": 5,
        "endInExample": 23
      },
      "levelSource": "dictionary_phrase",
      "ipa": "teɪk aʊt"
    },
    {
      "word": "terrifying",
      "lemma": "terrify",
      "lemmaId": "terrify",
      "pos": "adjective",
      "source": "word",
      "wordKey": "terrify_adjective",
      "level": "B2",
      "translations": {
        "ru": {
          "translation": "ужасать"
        }
      },
      "example": "”\n\n“My love, don’t be so terrifying,” Millie said, hooking her arm through Chrestomanci’s.",
      "exampleStart": 4212,
      "exampleEnd": 4302,
      "matchedForm": "terrifying",
      "levelSource": "vocabulary_index",
      "difficultyScore": 1,
      "difficultySource": "zipf"
    },
    {
      "word": "walk out",
      "lemma": "walk out",
      "lemmaId": "walk_out",
      "pos": "phrasal_verb",
      "type": "phrasal_verb",
      "source": "dictionary_phrasal",
      "wordKey": "walk_out_phrasal_verb",
      "level": "B2",
      "translations": {
        "ru": {
          "translation": "Выйди"
        }
      },
      "example": "When Millie and Chrestomanci had had nearly a minute in which to walk out of hearing, she said, “She’s sweet—Millie—an absolute honey.",
      "exampleStart": 4721,
      "exampleEnd": 4855,
      "phraseMatch": {
        "text": "walk out",
        "startInExample": 65,
        "endInExample": 73
      },
      "levelSource": "dictionary_phrase",
      "ipa": "wɔːk aʊt"
    }
  ]
}
